LICENSE
README.rst
pyproject.toml
setup.py
merlict/__init__.py
merlict/version_merlict_c89.py
merlict/version_python.py
merlict.egg-info/PKG-INFO
merlict.egg-info/SOURCES.txt
merlict.egg-info/dependency_links.txt
merlict.egg-info/requires.txt
merlict.egg-info/top_level.txt
merlict/c89/__init__.py
merlict/c89/almagamate_merlict_c89_and_set_version.py
merlict/c89/bridge.c
merlict/c89/bridge.h
merlict/c89/mli.c
merlict/c89/mli.h
merlict/c89/wrapper.c
merlict/c89/wrapper.pxd
merlict/c89/wrapper.pyx
merlict/intersection/__init__.py
merlict/intersectionSurfaceNormal/__init__.py
merlict/materials/__init__.py
merlict/materials/colors/__init__.py
merlict/materials/colors/cie1931/__init__.py
merlict/materials/colors/cie1931/rgb_matching_functions.py
merlict/materials/colors/cie1931/standard_observer.py
merlict/materials/media/__init__.py
merlict/materials/media/resources/pmma_T293K.json
merlict/materials/media/resources/vacuum.json
merlict/materials/media/resources/water_T293K.json
merlict/materials/spectra/__init__.py
merlict/materials/spectra/resources/perfect_absorber_reflection.csv
merlict/materials/spectra/resources/perfect_mirror_reflection.csv
merlict/materials/spectra/resources/pmma_T293K_absorption.csv
merlict/materials/spectra/resources/pmma_T293K_refraction.csv
merlict/materials/spectra/resources/vacuum_absorption.csv
merlict/materials/spectra/resources/vacuum_refraction.csv
merlict/materials/spectra/resources/water_T293K_absorption.csv
merlict/materials/spectra/resources/water_T293K_refraction.csv
merlict/materials/surfaces/__init__.py
merlict/materials/surfaces/resources/perfect_absorber.json
merlict/materials/surfaces/resources/perfect_mirror.json
merlict/materials/surfaces/resources/water.json
merlict/photon/__init__.py
merlict/photon/interaction.py
merlict/ray/__init__.py
merlict/scenery/__init__.py
merlict/scenery/string_format/__init__.py
merlict/scenery/string_format/convert.py
merlict/scenery/string_format/directory.py
merlict/scenery/string_format/fileorder.py
merlict/scenery/string_format/function_csv.py
merlict/scenery/string_format/tapearchive.py
merlict/tests/resources/segmented_reflector.tar
