Metadata-Version: 2.4
Name: merlict
Version: 0.2.5.2.2.7
Summary: Ray tracing in python
Home-page: https://github.com/cherenkov-plenoscope/merlict
Author: Sebastian Achim Mueller
Author-email: sebastian-achim.mueller@mpi-hd.mpg.de
Classifier: Programming Language :: Python :: 3
Classifier: License :: OSI Approved :: GNU General Public License v3 (GPLv3)
Classifier: Operating System :: OS Independent
Classifier: Natural Language :: English
Classifier: Topic :: Scientific/Engineering :: Physics
License-File: LICENSE
Requires-Dist: json_numpy_sebastian-achim-mueller
Requires-Dist: triangle_mesh_io>=0.0.2
Dynamic: author
Dynamic: author-email
Dynamic: classifier
Dynamic: description
Dynamic: description-content-type
Dynamic: home-page
Dynamic: license-file
Dynamic: requires-dist
Dynamic: summary
